[
  {
      "function": "minecraft:set_item",
      "item": "minecraft:torch",
      "conditions": [
        {
          "condition": "minecraft:entity_properties",
          "entity": "this",
          "predicate": {
            "slots": {
              "weapon.mainhand": {
                "items": "minecraft:stick",
                "count": 1,
                "predicates": {
                  "minecraft:enchantments": [
                    {
                      "enchantments": "gis:rpg_wand",
                      "levels": 1
                    }
                  ]
                }
              }
            }
          }
        }
      ]
    }
]